library_arq_python/__init__.py
library_arq_python-0.1.6.dist-info/METADATA
library_arq_python-0.1.6.dist-info/WHEEL
library_arq_python-0.1.6.dist-info/top_level.txt
library_arq_python-0.1.6.dist-info/RECORD
