Metadata-Version: 2.2
Name: library_arq_python
Version: 0.1.6
Summary: Una libreria simple de python
Requires-Python: >=3.8
